glog.py
glog-0.3.dist-info/DESCRIPTION.rst
glog-0.3.dist-info/METADATA
glog-0.3.dist-info/RECORD
glog-0.3.dist-info/WHEEL
glog-0.3.dist-info/metadata.json
glog-0.3.dist-info/top_level.txt
