Metadata-Version: 2.0
Name: glog
Version: 0.3
Summary: Simple Google-style logging wrapper for Python.
Home-page: https://github.com/benley/python-glog
Author: Benjamin Staffin
Author-email: benley@gmail.com
License: BSD
Platform: any
Classifier: Programming Language :: Python
Classifier: Development Status :: 4 - Beta
Classifier: Intended Audience :: Developers
Classifier: License :: OSI Approved :: BSD License
Classifier: Topic :: System :: Logging
Classifier: Topic :: Software Development :: Libraries :: Python Modules
Requires-Dist: python-gflags (>=3.0)
